uniform_vlm_infer/__init__.py
uniform_vlm_infer/cli.py
uniform_vlm_infer/dataset.py
uniform_vlm_infer/format.py
uniform_vlm_infer/infer.py
uniform_vlm_infer/warmup.py
uniform_vlm_infer-0.1.1.dist-info/METADATA
uniform_vlm_infer-0.1.1.dist-info/WHEEL
uniform_vlm_infer-0.1.1.dist-info/entry_points.txt
uniform_vlm_infer-0.1.1.dist-info/top_level.txt
uniform_vlm_infer-0.1.1.dist-info/RECORD
