Metadata-Version: 2.4
Name: uniform-vlm-infer
Version: 0.1.1
Summary: Easy one‑liner inference + post‑processing for the uniform LoRA VLM.
Author-email: Dillon Murphy <ddmurphy@calpoly.edu>, Kailyn Kragas <kkragas@calpoly.edu>, Sofia Bryukhova <sbryukho@calpoly.edu>, Jasmine Cabrera <jkscabrera2003@gmail.com>
Requires-Python: >=3.9
Requires-Dist: pandas>=2.0
Requires-Dist: huggingface_hub>=0.22
Requires-Dist: ms-swift
